{"gameData":{"remit":[[{"id":336,"name":"Spanish League Top Scorer","type":6,"displayName":"LaLiga Golden Boot","helperText":"data is available from 1960/61 onwards"}],[{"id":16,"name":"Uruguay","type":1,"displayName":"URU"}],[{"id":147,"name":"Sevilla","type":2,"displayName":"SEV"}],[{"id":186,"name":"Porto","type":2,"displayName":"POR"}],[{"id":2,"name":"Spain","type":1,"displayName":"ESP"},{"id":179,"name":"Chelsea","type":2,"displayName":"CHE"}],[{"id":1,"name":"England","type":1,"displayName":"ENG"}],[{"id":35,"name":"United States","type":1,"displayName":"USA"}],[{"id":172,"name":"Paris Saint-Germain","type":2,"displayName":"PSG"}],[{"id":112,"name":"Barcelona","type":2,"displayName":"BAR"}],[{"id":319,"name":"Ángel Di María","type":5,"displayName":"Di María","prefix":"Played with"}],[{"id":33,"name":"Austria","type":1,"displayName":"AUT"}],[{"id":402,"name":"CONCACAF","type":1,"displayName":"N/C America or Carribean","helperText":"players from countries in CONCACAF, which includes USA, Mexico, Costa Rica, Jamaica and others — not just based on geographic location."}],[{"id":373,"name":"Scottish Premiership","type":3,"displayName":"Scottish Premiership","prefix":"Played in","helperText":"data is available from 1997/98 onwards"}],[{"id":354,"name":"World Cup","type":6,"displayName":"World Cup","suffix":"winner","helperText":"data is available from 1958 onwards"}],[{"id":313,"name":"Diego Simeone","type":4,"displayName":"Simeone","prefix":"Managed by"}],[{"id":426,"name":"Uefa Cup || Europa League","type":6,"displayName":"Uefa Cup / Europa League","suffix":"winner"}]],"players":[{"id":6874,"f":"Pandev","g":"Goran","v":[]},{"id":3471,"f":"Haller","g":"Sebastien","v":[]},{"id":2625,"f":"Morata","g":"Alvaro","v":[2,179,313,319,426]},{"id":2576,"f":"Savic","g":"Stefan","v":[313,426]},{"id":401,"f":"Modeste","g":"Anthony","v":[]},{"id":793,"f":"Dida","g":"","v":[354],"b":"07/10/1973"},{"id":13249,"f":"Alex Sandro","g":"","v":[186,319]},{"id":4606,"f":"Laimer","g":"Konrad","v":[33]},{"id":10423,"f":"Martial","g":"Anthony","v":[147,426]},{"id":32629,"f":"Rashford","g":"Marcus","v":[1,426]},{"id":1319,"f":"Toure","g":"Kolo","v":[373]},{"id":45396,"f":"Dovbyk","g":"Artem","v":[336]},{"id":18920,"f":"Acuna","g":"Marcos","v":[147,319,354,426]},{"id":54440,"f":"Buchanan","g":"Tajon","v":[402]},{"id":9616,"f":"Edwards","g":"Marcus","v":[1]},{"id":2117,"f":"Pedro","g":"","v":[2,112,179,354,426],"b":"28/07/1987"},{"id":44509,"f":"Tsygankov","g":"Viktor","v":[]},{"id":7278,"f":"Cisse","g":"Papiss Demba","v":[]},{"id":912,"f":"Beckham","g":"David","v":[1,172]},{"id":9119,"f":"de Boer","g":"Frank","v":[112,373,426]},{"id":6696,"f":"Zamorano","g":"Ivan","v":[147,336,426]},{"id":7048,"f":"Dumfries","g":"Denzel","v":[402]},{"id":9171,"f":"Larsson","g":"Henrik","v":[112,373]},{"id":1512,"f":"Balogun","g":"Folarin","v":[35,402]},{"id":21545,"f":"Cash","g":"Matty","v":[]},{"id":1101,"f":"Tonali","g":"Sandro","v":[]},{"id":3413,"f":"Akanji","g":"Manuel","v":[]},{"id":1461,"f":"Sanchez","g":"Alexis","v":[112,313]},{"id":8290,"f":"Osimhen","g":"Victor","v":[]},{"id":23387,"f":"Valverde","g":"Federico","v":[16]},{"id":1998,"f":"Paredes","g":"Leandro","v":[172,319,354]},{"id":9660,"f":"Bentancur","g":"Rodrigo","v":[16,426]},{"id":28654,"f":"Otavio","g":"","v":[186],"b":"09/02/1995"},{"id":23367,"f":"Navas","g":"Keylor","v":[172,319,402]},{"id":3735,"f":"ter Stegen","g":"Marc-Andre","v":[112]},{"id":9202,"f":"Dani Alves","g":"","v":[112,147,172,319,426]},{"id":18820,"f":"Ramos","g":"Sergio","v":[2,147,172,319,354]},{"id":2480,"f":"Motta","g":"Thiago","v":[112,172,319]},{"id":6952,"f":"Vidic","g":"Nemanja","v":[]},{"id":5665,"f":"Fuchs","g":"Christian","v":[33]},{"id":3403,"f":"Pulisic","g":"Christian","v":[35,179,402]},{"id":1547,"f":"Jorginho","g":"","v":[179,426],"b":"20/12/1991"}]}}