{"gameData":{"remit":[[{"id":289,"name":"Liga Portugal","type":3,"displayName":"Liga Portugal","dataFrom":"1990/91"}],[{"id":160,"name":"Real Madrid","type":2,"displayName":"RMA"},{"id":179,"name":"Chelsea","type":2,"displayName":"CHE"}],[{"id":12,"name":"Italy","type":1,"displayName":"ITA"}],[{"id":10,"name":"Germany","type":1,"displayName":"GER"}],[{"id":93,"name":"Liverpool","type":2,"displayName":"LIV"}],[{"id":355,"name":"Euros","type":6,"displayName":"Euros"}],[{"id":117,"name":"AS Monaco","type":2,"displayName":"AMO"}],[{"id":333,"name":"Premier League Top Scorer","type":6,"displayName":"English Top Div Golden Boot","dataFrom":"1992/93"}],[{"id":320,"name":"Gianluigi Buffon","type":5,"displayName":"Buffon"}],[{"id":352,"name":"Champions League","type":6,"displayName":"Champions Lge","dataFrom":"1992/93"}],[{"id":114,"name":"Tottenham Hotspur","type":2,"displayName":"TOT"}],[{"id":8,"name":"Netherlands","type":1,"displayName":"NLD"}],[{"id":307,"name":"Jürgen Klopp","type":4,"displayName":"Klopp"}],[{"id":21,"name":"Chile","type":1,"displayName":"CHL"}],[{"id":176,"name":"Ajax","type":2,"displayName":"AJA"}],[{"id":86,"name":"Atlético Madrid","type":2,"displayName":"ATM"}]],"players":[{"id":5818,"f":"Ambrosini","g":"Massimo","v":[12,320,352]},{"id":74842,"f":"Gotze","g":"Mario","v":[10,307]},{"id":132,"f":"Rosicky","g":"Tomas","v":[]},{"id":139208,"f":"van Dijk","g":"Virgil","v":[8,93,307,352]},{"id":148455,"f":"Mohamed Salah","g":"","v":[93,179,307,333,352]},{"id":553875,"f":"Porro","g":"Pedro","v":[114,289]},{"id":484547,"f":"Frimpong","g":"Jeremie","v":[8]},{"id":9828,"f":"Carvalho","g":"Ricardo","v":[117,160,179,289,352,355]},{"id":58088,"f":"Muslera","g":"Fernando","v":[]},{"id":7514,"f":"Helguera","g":"Ivan","v":[160,352]},{"id":16911,"f":"Schmeichel","g":"Kasper","v":[]},{"id":387626,"f":"Bailey","g":"Leon","v":[]},{"id":524481,"f":"Roger Ibanez","g":"","v":[]},{"id":37666,"f":"Vidal","g":"Arturo","v":[21,320]},{"id":111455,"f":"Xhaka","g":"Granit","v":[]},{"id":10,"f":"Klose","g":"Miroslav","v":[10]},{"id":60444,"f":"Alcantara","g":"Thiago","v":[93,307,352]},{"id":478573,"f":"Gravenberch","g":"Ryan","v":[8,93,176,307]},{"id":4375,"f":"Reiziger","g":"Michael","v":[8,176,352]},{"id":513245,"f":"Lindstrom","g":"Jesper","v":[]},{"id":401922,"f":"Chukwueze","g":"Samuel","v":[]},{"id":129083,"f":"Zamorano","g":"Ivan","v":[21,160]},{"id":122153,"f":"Pogba","g":"Paul","v":[320]},{"id":1397,"f":"Owen","g":"Michael","v":[93,160,333]},{"id":18922,"f":"Benzema","g":"Karim","v":[160,352]},{"id":3163,"f":"Lampard","g":"Frank","v":[179,352],"b":"20/06/1978"},{"id":170527,"f":"Werner","g":"Timo","v":[10,114,179,352]},{"id":8564,"f":"Deco","g":"","v":[179,289,352]},{"id":50570,"f":"Lavezzi","g":"Ezequiel","v":[]},{"id":39983,"f":"Bonucci","g":"Leonardo","v":[12,320,355]},{"id":277179,"f":"Angelino","g":"","v":[]},{"id":50202,"f":"Hazard","g":"Eden","v":[160,179,352]},{"id":525247,"f":"Kilman","g":"Maximilian","v":[]},{"id":4188,"f":"Quaresma","g":"Ricardo","v":[179,289,352,355]},{"id":27577,"f":"Dempsey","g":"Clint","v":[114]},{"id":8019,"f":"Simao","g":"","v":[86,289],"b":"31/10/1979"},{"id":7767,"f":"Torres","g":"Fernando","v":[86,93,179,352,355]},{"id":4257,"f":"Eto'o","g":"Samuel","v":[160,179,352]},{"id":33706,"f":"Nani","g":"","v":[289,352,355]},{"id":3207,"f":"Henry","g":"Thierry","v":[117,333,352,355]},{"id":238055,"f":"Rafa","g":"","v":[289,355],"b":"17/05/1993"},{"id":3291,"f":"Barry","g":"Gareth","v":[]}]}}