{"gameData":{"remit":[[{"id":179,"name":"Chelsea","type":2,"displayName":"CHE"}],[{"id":99,"name":"Inter Milan","type":2,"displayName":"INT"}],[{"id":1,"name":"England","type":1,"displayName":"ENG"}],[{"id":176,"name":"Ajax","type":2,"displayName":"AJA"}],[{"id":12,"name":"Italy","type":1,"displayName":"ITA"}],[{"id":36,"name":"Czech Republic","type":1,"displayName":"CZE"}],[{"id":352,"name":"Champions League","type":6,"displayName":"Champions Lge","dataFrom":"1992/93"}],[{"id":160,"name":"Real Madrid","type":2,"displayName":"RMA"}],[{"id":333,"name":"Premier League Top Scorer","type":6,"displayName":"English Top Div Golden Boot","dataFrom":"1992/93"}],[{"id":355,"name":"Euros","type":6,"displayName":"Euros"}],[{"id":5,"name":"Portugal","type":1,"displayName":"POR"}],[{"id":2,"name":"Spain","type":1,"displayName":"ESP"},{"id":83,"name":"AC Milan","type":2,"displayName":"MIL"}],[{"id":141,"name":"Sporting CP","type":2,"displayName":"SCP"}],[{"id":330,"name":"James Milner","type":5,"displayName":"Milner"}],[{"id":373,"name":"Scottish Premiership","type":3,"displayName":"Scottish Top Div","dataFrom":"1997/98"}],[{"id":310,"name":"Luis Enrique","type":4,"displayName":"Enrique"}]],"players":[{"id":111873,"f":"Martinez","g":"Emiliano","v":[],"b":"02/09/1992"},{"id":1725,"f":"Christiansen","g":"Jesper","v":[373]},{"id":4375,"f":"Reiziger","g":"Michael","v":[83,176,352]},{"id":395516,"f":"Diaby","g":"Moussa","v":[]},{"id":3924,"f":"Drogba","g":"Didier","v":[179,333,352]},{"id":44352,"f":"Suarez","g":"Luis","v":[176,310,333,352],"b":"24/01/1987"},{"id":23951,"f":"Mandanda","g":"Steve","v":[]},{"id":287579,"f":"Amrabat","g":"Sofyan","v":[]},{"id":616341,"f":"Mendes","g":"Nuno","v":[5,141,310],"b":"19/06/2002"},{"id":40433,"f":"Sanchez","g":"Alexis","v":[99]},{"id":63,"f":"Ballack","g":"Michael","v":[179]},{"id":46580,"f":"Kramaric","g":"Andrej","v":[]},{"id":206050,"f":"Dybala","g":"Paulo","v":[]},{"id":105521,"f":"Immobile","g":"Ciro","v":[12,355]},{"id":34557,"f":"Bendtner","g":"Nicklas","v":[]},{"id":198008,"f":"Silva","g":"Andre","v":[5,83],"b":"06/11/1995"},{"id":484547,"f":"Frimpong","g":"Jeremie","v":[373]},{"id":517894,"f":"Cunha","g":"Matheus","v":[],"b":"27/05/1999"},{"id":3393,"f":"Silvestre","g":"Mikael","v":[99,352]},{"id":238055,"f":"Rafa","g":"","v":[5,355],"b":"17/05/1993"},{"id":3597,"f":"Carragher","g":"Jamie","v":[1,330,352]},{"id":5658,"f":"Cech","g":"Petr","v":[36,179,352]},{"id":4317,"f":"Maxwell","g":"","v":[99,176,352],"b":"27/08/1981"},{"id":255508,"f":"Williams","g":"Inaki","v":[]},{"id":274839,"f":"Ndidi","g":"Wilfred","v":[]},{"id":42460,"f":"Perisic","g":"Ivan","v":[99,352]},{"id":200512,"f":"Mane","g":"Sadio","v":[330,333,352]},{"id":91845,"f":"Son","g":"Heung-min","v":[333]},{"id":5940,"f":"Panucci","g":"Christian","v":[12,83,99,160,179,352]},{"id":128223,"f":"Morata","g":"Alvaro","v":[2,83,160,179,310,352,355]},{"id":122153,"f":"Pogba","g":"Paul","v":[]},{"id":238223,"f":"Ederson","g":"","v":[352],"b":"17/08/1993"},{"id":22068,"f":"Ribery","g":"Franck","v":[352]},{"id":7825,"f":"Reina","g":"Pepe","v":[2,83,355]},{"id":27577,"f":"Dempsey","g":"Clint","v":[]},{"id":454567,"f":"Kokcu","g":"Orkun","v":[]},{"id":125781,"f":"Griezmann","g":"Antoine","v":[]},{"id":192565,"f":"Sane","g":"Leroy","v":[]},{"id":1397,"f":"Owen","g":"Michael","v":[1,160,330,333]},{"id":265088,"f":"Locatelli","g":"Manuel","v":[12,83,355]},{"id":552057,"f":"Hlozek","g":"Adam","v":[36]},{"id":411295,"f":"Raphinha","g":"","v":[141],"b":"14/12/1996"}]}}