{"gameData":{"remit":[[{"id":55,"name":"Canada","type":1,"displayName":"CAN"}],[{"id":288,"name":"Eredivisie","type":3,"displayName":"Dutch Top Div","dataFrom":"1956/57"}],[{"id":8,"name":"Netherlands","type":1,"displayName":"NLD"}],[{"id":12,"name":"Italy","type":1,"displayName":"ITA"}],[{"id":330,"name":"James Milner","type":5,"displayName":"Milner"}],[{"id":99,"name":"Inter Milan","type":2,"displayName":"INT"}],[{"id":183,"name":"Real Sociedad","type":2,"displayName":"SOC"}],[{"id":5,"name":"Portugal","type":1,"displayName":"POR"}],[{"id":333,"name":"Premier League Top Scorer","type":6,"displayName":"English Top Div Golden Boot","dataFrom":"1992/93"}],[{"id":112,"name":"Barcelona","type":2,"displayName":"BAR"}],[{"id":176,"name":"Ajax","type":2,"displayName":"AJA"}],[{"id":308,"name":"Thomas Tuchel","type":4,"displayName":"Tuchel"}],[{"id":3,"name":"France","type":1,"displayName":"FRA"},{"id":204,"name":"Manchester United","type":2,"displayName":"MUN"}],[{"id":147,"name":"Sevilla","type":2,"displayName":"SEV"}],[{"id":427,"name":"Champions League || European Cup Golden Boot","type":6,"displayName":"Champions League Or European Cup Golden Boot"}],[{"id":356,"name":"Copa América","type":6,"displayName":"Copa América","dataFrom":"1960"}]],"players":[{"id":7767,"f":"Torres","g":"Fernando","v":[]},{"id":191891,"f":"Milik","g":"Arkadiusz","v":[176,288]},{"id":22412,"f":"Julio Cesar","g":"","v":[99,356],"b":"03/09/1979"},{"id":315853,"f":"Bastoni","g":"Alessandro","v":[12,99]},{"id":41384,"f":"Arnautovic","g":"Marko","v":[99,288]},{"id":122153,"f":"Pogba","g":"Paul","v":[3,204]},{"id":10,"f":"Klose","g":"Miroslav","v":[]},{"id":420243,"f":"Timber","g":"Jurrien","v":[8,176,288]},{"id":516716,"f":"Bremer","g":"","v":[]},{"id":60410,"f":"Acuna","g":"Marcos","v":[147,356]},{"id":7825,"f":"Reina","g":"Pepe","v":[112]},{"id":406040,"f":"Lookman","g":"Ademola","v":[]},{"id":61651,"f":"Henderson","g":"Jordan","v":[176,288,308,330]},{"id":182877,"f":"Martial","g":"Anthony","v":[3,147,204]},{"id":4010,"f":"Kuyt","g":"Dirk","v":[8,288]},{"id":108880,"f":"Casteels","g":"Koen","v":[]},{"id":552057,"f":"Hlozek","g":"Adam","v":[]},{"id":5800,"f":"Dida","g":"","v":[356],"b":"07/10/1973"},{"id":164770,"f":"Varane","g":"Raphael","v":[3,204]},{"id":72522,"f":"de Jong","g":"Luuk","v":[8,112,147,288]},{"id":181375,"f":"Haller","g":"Sebastien","v":[176,288]},{"id":7476,"f":"Alonso","g":"Xabi","v":[183]},{"id":58864,"f":"Aubameyang","g":"Pierre-Emerick","v":[112,308,333]},{"id":38253,"f":"Lewandowski","g":"Robert","v":[112,427]},{"id":5758,"f":"Davids","g":"Edgar","v":[8,99,112,176,288]},{"id":26399,"f":"Aguero","g":"Sergio","v":[112,330,333,356]},{"id":351478,"f":"Oyarzabal","g":"Mikel","v":[183]},{"id":14942,"f":"Srna","g":"Darijo","v":[]},{"id":32467,"f":"Rakitic","g":"Ivan","v":[112,147]},{"id":3994,"f":"Makaay","g":"Roy","v":[8,288]},{"id":424204,"f":"Davies","g":"Alphonso","v":[55,308]},{"id":533738,"f":"David","g":"Jonathan","v":[55]},{"id":341092,"f":"Chiesa","g":"Federico","v":[12]},{"id":33706,"f":"Nani","g":"","v":[5,204]},{"id":709187,"f":"Williams","g":"Nico","v":[]},{"id":314875,"f":"Bowen","g":"Jarrod","v":[308]},{"id":18922,"f":"Benzema","g":"Karim","v":[3,427]},{"id":537860,"f":"Mudryk","g":"Mykhaylo","v":[]},{"id":487465,"f":"Neto","g":"Pedro","v":[5]},{"id":148455,"f":"Mohamed Salah","g":"","v":[330,333]},{"id":442531,"f":"Mendy","g":"Edouard","v":[308]},{"id":5748,"f":"Tacchinardi","g":"Alessio","v":[12]}]}}